ocr_agl/.DS_Store
ocr_agl/Makefile
ocr_agl/__init__.py
ocr_agl/app.py
ocr_agl/build/doctrees/environment.pickle
ocr_agl/build/doctrees/index.doctree
ocr_agl/build/html/.buildinfo
ocr_agl/build/html/_sources/index.rst.txt
ocr_agl/build/html/_static/alabaster.css
ocr_agl/build/html/_static/basic.css
ocr_agl/build/html/_static/custom.css
ocr_agl/build/html/_static/doctools.js
ocr_agl/build/html/_static/documentation_options.js
ocr_agl/build/html/_static/file.png
ocr_agl/build/html/_static/language_data.js
ocr_agl/build/html/_static/minus.png
ocr_agl/build/html/_static/plus.png
ocr_agl/build/html/_static/pygments.css
ocr_agl/build/html/_static/searchtools.js
ocr_agl/build/html/_static/sphinx_highlight.js
ocr_agl/build/html/genindex.html
ocr_agl/build/html/index.html
ocr_agl/build/html/objects.inv
ocr_agl/build/html/search.html
ocr_agl/build/html/searchindex.js
ocr_agl/make.bat
ocr_agl/pytesseract-master/.DS_Store
ocr_agl/pytesseract-master/.github/workflows/ci.yaml
ocr_agl/pytesseract-master/.gitignore
ocr_agl/pytesseract-master/.pre-commit-config.yaml
ocr_agl/pytesseract-master/LICENSE
ocr_agl/pytesseract-master/README.rst
ocr_agl/pytesseract-master/pyproject.toml
ocr_agl/pytesseract-master/pytesseract/__init__.py
ocr_agl/pytesseract-master/pytesseract/pytesseract.py
ocr_agl/pytesseract-master/requirements-dev.txt
ocr_agl/pytesseract-master/setup.cfg
ocr_agl/pytesseract-master/setup.py
ocr_agl/pytesseract-master/tests/.DS_Store
ocr_agl/pytesseract-master/tests/data/images.txt
ocr_agl/pytesseract-master/tests/data/test-european.jpg
ocr_agl/pytesseract-master/tests/data/test-small.jpg
ocr_agl/pytesseract-master/tests/data/test.bmp
ocr_agl/pytesseract-master/tests/data/test.gif
ocr_agl/pytesseract-master/tests/data/test.jpeg2000
ocr_agl/pytesseract-master/tests/data/test.jpg
ocr_agl/pytesseract-master/tests/data/test.pgm
ocr_agl/pytesseract-master/tests/data/test.png
ocr_agl/pytesseract-master/tests/data/test.ppm
ocr_agl/pytesseract-master/tests/data/test.tiff
agl_ocr_reader-1.1.1.dist-info/LICENSE
agl_ocr_reader-1.1.1.dist-info/METADATA
agl_ocr_reader-1.1.1.dist-info/WHEEL
agl_ocr_reader-1.1.1.dist-info/RECORD
